celltypist/__init__.py
celltypist/annotate.py
celltypist/classifier.py
celltypist/command_line.py
celltypist/logger.py
celltypist/models.py
celltypist/samples.py
celltypist/data/samples/sample_cell_by_gene.csv
celltypist_dev-0.1.15.dist-info/LICENSE
celltypist_dev-0.1.15.dist-info/METADATA
celltypist_dev-0.1.15.dist-info/WHEEL
celltypist_dev-0.1.15.dist-info/entry_points.txt
celltypist_dev-0.1.15.dist-info/top_level.txt
celltypist_dev-0.1.15.dist-info/RECORD
