Metadata-Version: 2.1
Name: celltypist-dev
Version: 0.1.15
Summary: A tool for semi-automatic cell type annotation
Home-page: https://github.com/cellgeni/celltypist
Author: Chuan Xu
Author-email: cx1@sanger.ac.uk
License: UNKNOWN
Platform: UNKNOWN
Classifier: Programming Language :: Python :: 3
Classifier: Operating System :: OS Independent
Classifier: Intended Audience :: Science/Research
Classifier: Topic :: Scientific/Engineering :: Bio-Informatics
Classifier: Development Status :: 4 - Beta
Requires-Python: >=3.8
Requires-Dist: numpy (>=1.19.0)
Requires-Dist: pandas (>=1.0.5)
Requires-Dist: scikit-learn (>=0.24.1)
Requires-Dist: openpyxl (>=3.0.4)
Requires-Dist: click (>=7.1.2)
Requires-Dist: requests (>=2.23.0)
Requires-Dist: scanpy (>=1.7.0)
Requires-Dist: leidenalg (>=0.8.3)
